setup.cfg
setup.py
pyreactor/__init__.py
pyreactor/reactor.py
pyreactor.egg-info/PKG-INFO
pyreactor.egg-info/SOURCES.txt
pyreactor.egg-info/dependency_links.txt
pyreactor.egg-info/top_level.txt
pyreactor.egg-info/zip-safe
tests/__init__.py
tests/conftest.py
tests/test_reactor.py