Metadata-Version: 1.1
Name: pyreactor
Version: 1.0.0
Summary: A feedback based reactor pattern.
Home-page: https://github.com/verisign/pyreactor
Author: Kinnar Dattani
Author-email: kdattani@verisign.com
License: UNKNOWN
Download-URL: https://github.com/verisign/pyreactor/archive/v1.0.tar.gz
Keywords: reactor pattern
Platform: UNKNOWN
